{
  "products": [
    {
      "_id": "1",
      "title": "Book 1",
      "description": "Là một trong những quyển sách Việt Nam bán chạy nhất năm 2010, Tôi thấy hoa vàng trên cỏ xanh đã được tái bản ngay trong ngày phát hành đầu tiên, với tổng số bản in lên đến hơn 20.000 bản.",
      "content": "Một câu chuyện dài lắm",
      "price": 23,
      "count": 13,
      "image": "https://images.unsplash.com/photo-1668454145710-0629d353866d?ixlib=rb-4.0.3&ixid=MnwxMjA3fDB8MHxwaG90by1wYWdlfHx8fGVufDB8fHx8&auto=format&fit=crop&w=987&q=80",
      "author": "Nguyễn Nhật Ánh",
      "genre": "novel",
      "publisher": "NXB Tuổi Trẻ",
      "pages": "300",
      "language": "Tiếng Việt",
      "feedbacks": [
        {
          "idx": "1",
          "name": "Joji",
          "img": "https://i.pinimg.com/736x/fa/7f/4b/fa7f4b715e0bd97be8513d0179ef795d.jpg",
          "comment": "Poor",
          "rating": "1"
        },
        {
          "idx": "2",
          "name": "Cristiano",
          "img": "https://i.pinimg.com/736x/38/29/fb/3829fb37e22dc3ae8fb0e834b33602cc.jpg",
          "comment": "Siiiiiiiiiiii",
          "rating": "3"
        },
        {
          "idx": "3",
          "name": "Michael Rosen",
          "img": "https://i.pinimg.com/736x/c3/67/ce/c367ce675b571ef852f1835cb3fed499.jpg",
          "comment": "Nice",
          "rating": "5"
        }
      ]
    },
    {
      "_id": "2",
      "title": "Book 2",
      "description": "Là một trong những quyển sách Việt Nam bán chạy nhất năm 2010, Tôi thấy hoa vàng trên cỏ xanh đã được tái bản ngay trong ngày phát hành đầu tiên, với tổng số bản in lên đến hơn 20.000 bản.",
      "content": "Một câu chuyện dài lắm",
      "price": 19,
      "count": 15,
      "image": "https://images.unsplash.com/photo-1668454145710-0629d353866d?ixlib=rb-4.0.3&ixid=MnwxMjA3fDB8MHxwaG90by1wYWdlfHx8fGVufDB8fHx8&auto=format&fit=crop&w=987&q=80",
      "author": "Nguyễn Nhật Ánh",
      "genre": "novel",
      "publisher": "NXB Tuổi Trẻ",
      "pages": "300",
      "language": "Tiếng Việt",
      "feedbacks": [
        {
          "idx": "1",
          "name": "Joji",
          "img": "https://i.pinimg.com/736x/fa/7f/4b/fa7f4b715e0bd97be8513d0179ef795d.jpg",
          "comment": "Poor",
          "rating": "1"
        },
        {
          "idx": "2",
          "name": "Cristiano",
          "img": "https://i.pinimg.com/736x/38/29/fb/3829fb37e22dc3ae8fb0e834b33602cc.jpg",
          "comment": "Siiiiiiiiiiii",
          "rating": "3"
        },
        {
          "idx": "3",
          "name": "Michael Rosen",
          "img": "https://i.pinimg.com/736x/c3/67/ce/c367ce675b571ef852f1835cb3fed499.jpg",
          "comment": "Nice",
          "rating": "5"
        }
      ]
    },
    {
      "_id": "3",
      "title": "Book 3",
      "description": "Là một trong những quyển sách Việt Nam bán chạy nhất năm 2010, Tôi thấy hoa vàng trên cỏ xanh đã được tái bản ngay trong ngày phát hành đầu tiên, với tổng số bản in lên đến hơn 20.000 bản.",
      "content": "Một câu chuyện dài lắm",
      "price": 50,
      "count": 16,
      "image": "https://images.unsplash.com/photo-1541963463532-d68292c34b19?ixlib=rb-4.0.3&ixid=MnwxMjA3fDB8MHxwaG90by1wYWdlfHx8fGVufDB8fHx8&auto=format&fit=crop&w=988&q=80",
      "author": "Nguyễn Nhật Ánh",
      "genre": "novel",
      "publisher": "NXB Tuổi Trẻ",
      "pages": "300",
      "language": "Tiếng Việt",
      "feedbacks": [
        {
          "idx": "1",
          "name": "Joji",
          "img": "https://i.pinimg.com/736x/fa/7f/4b/fa7f4b715e0bd97be8513d0179ef795d.jpg",
          "comment": "Poor",
          "rating": "1"
        },
        {
          "idx": "2",
          "name": "Cristiano",
          "img": "https://i.pinimg.com/736x/38/29/fb/3829fb37e22dc3ae8fb0e834b33602cc.jpg",
          "comment": "Siiiiiiiiiiii",
          "rating": "3"
        },
        {
          "idx": "3",
          "name": "Michael Rosen",
          "img": "https://i.pinimg.com/736x/c3/67/ce/c367ce675b571ef852f1835cb3fed499.jpg",
          "comment": "Nice",
          "rating": "5"
        }
      ]
    },
    {
      "_id": "4",
      "title": "Book 4",
      "description": "Là một trong những quyển sách Việt Nam bán chạy nhất năm 2010, Tôi thấy hoa vàng trên cỏ xanh đã được tái bản ngay trong ngày phát hành đầu tiên, với tổng số bản in lên đến hơn 20.000 bản.",
      "content": "Một câu chuyện dài lắm",
      "price": 15,
      "count": 13,
      "image": "https://images.unsplash.com/photo-1668454145710-0629d353866d?ixlib=rb-4.0.3&ixid=MnwxMjA3fDB8MHxwaG90by1wYWdlfHx8fGVufDB8fHx8&auto=format&fit=crop&w=987&q=80",
      "author": "Nguyễn Nhật Ánh",
      "genre": "novel",
      "publisher": "NXB Tuổi Trẻ",
      "pages": "300",
      "language": "Tiếng Việt",
      "feedbacks": [
        {
          "idx": "1",
          "name": "Joji",
          "img": "https://i.pinimg.com/736x/fa/7f/4b/fa7f4b715e0bd97be8513d0179ef795d.jpg",
          "comment": "Poor",
          "rating": "1"
        },
        {
          "idx": "2",
          "name": "Cristiano",
          "img": "https://i.pinimg.com/736x/38/29/fb/3829fb37e22dc3ae8fb0e834b33602cc.jpg",
          "comment": "Siiiiiiiiiiii",
          "rating": "3"
        },
        {
          "idx": "3",
          "name": "Michael Rosen",
          "img": "https://i.pinimg.com/736x/c3/67/ce/c367ce675b571ef852f1835cb3fed499.jpg",
          "comment": "Nice",
          "rating": "5"
        }
      ]
    },
    {
      "_id": "5",
      "title": "Book 5",
      "description": "Là một trong những quyển sách Việt Nam bán chạy nhất năm 2010, Tôi thấy hoa vàng trên cỏ xanh đã được tái bản ngay trong ngày phát hành đầu tiên, với tổng số bản in lên đến hơn 20.000 bản.",
      "content": "Một câu chuyện dài lắm",
      "price": 10,
      "count": 22,
      "image": "https://images.unsplash.com/photo-1668434177416-525261283120?ixlib=rb-4.0.3&ixid=MnwxMjA3fDB8MHxwaG90by1wYWdlfHx8fGVufDB8fHx8&auto=format&fit=crop&w=1035&q=80",
      "author": "Nguyễn Nhật Ánh",
      "genre": "novel",
      "publisher": "NXB Tuổi Trẻ",
      "pages": "300",
      "language": "Tiếng Việt",
      "feedbacks": [
        {
          "idx": "1",
          "name": "Joji",
          "img": "https://i.pinimg.com/736x/fa/7f/4b/fa7f4b715e0bd97be8513d0179ef795d.jpg",
          "comment": "Poor",
          "rating": "1"
        },
        {
          "idx": "2",
          "name": "Cristiano",
          "img": "https://i.pinimg.com/736x/38/29/fb/3829fb37e22dc3ae8fb0e834b33602cc.jpg",
          "comment": "Siiiiiiiiiiii",
          "rating": "3"
        },
        {
          "idx": "3",
          "name": "Michael Rosen",
          "img": "https://i.pinimg.com/736x/c3/67/ce/c367ce675b571ef852f1835cb3fed499.jpg",
          "comment": "Nice",
          "rating": "5"
        }
      ]
    },
    {
      "_id": "6",
      "title": "Book 6",
      "description": "Là một trong những quyển sách Việt Nam bán chạy nhất năm 2010, Tôi thấy hoa vàng trên cỏ xanh đã được tái bản ngay trong ngày phát hành đầu tiên, với tổng số bản in lên đến hơn 20.000 bản.",
      "content": "Một câu chuyện dài lắm",
      "price": 17,
      "count": 15,
      "image": "https://images.unsplash.com/photo-1668434177416-525261283120?ixlib=rb-4.0.3&ixid=MnwxMjA3fDB8MHxwaG90by1wYWdlfHx8fGVufDB8fHx8&auto=format&fit=crop&w=1035&q=80",
      "author": "Nguyễn Nhật Ánh",
      "genre": "novel",
      "publisher": "NXB Tuổi Trẻ",
      "pages": "300",
      "language": "Tiếng Việt",
      "feedbacks": [
        {
          "idx": "1",
          "name": "Joji",
          "img": "https://i.pinimg.com/736x/fa/7f/4b/fa7f4b715e0bd97be8513d0179ef795d.jpg",
          "comment": "Poor",
          "rating": "1"
        },
        {
          "idx": "2",
          "name": "Cristiano",
          "img": "https://i.pinimg.com/736x/38/29/fb/3829fb37e22dc3ae8fb0e834b33602cc.jpg",
          "comment": "Siiiiiiiiiiii",
          "rating": "3"
        },
        {
          "idx": "3",
          "name": "Michael Rosen",
          "img": "https://i.pinimg.com/736x/c3/67/ce/c367ce675b571ef852f1835cb3fed499.jpg",
          "comment": "Nice",
          "rating": "5"
        }
      ]
    },
    {
      "_id": "7",
      "title": "Book 7",
      "description": "Là một trong những quyển sách Việt Nam bán chạy nhất năm 2010, Tôi thấy hoa vàng trên cỏ xanh đã được tái bản ngay trong ngày phát hành đầu tiên, với tổng số bản in lên đến hơn 20.000 bản.",
      "content": "Một câu chuyện dài lắm",
      "price": 17,
      "count": 15,
      "image": "https://images.unsplash.com/photo-1668434177416-525261283120?ixlib=rb-4.0.3&ixid=MnwxMjA3fDB8MHxwaG90by1wYWdlfHx8fGVufDB8fHx8&auto=format&fit=crop&w=1035&q=80",
      "author": "Nguyễn Nhật Ánh",
      "genre": "novel",
      "publisher": "NXB Tuổi Trẻ",
      "pages": "300",
      "language": "Tiếng Việt",
      "feedbacks": [
        {
          "idx": "1",
          "name": "Joji",
          "img": "https://i.pinimg.com/736x/fa/7f/4b/fa7f4b715e0bd97be8513d0179ef795d.jpg",
          "comment": "Poor",
          "rating": "1"
        },
        {
          "idx": "2",
          "name": "Cristiano",
          "img": "https://i.pinimg.com/736x/38/29/fb/3829fb37e22dc3ae8fb0e834b33602cc.jpg",
          "comment": "Siiiiiiiiiiii",
          "rating": "3"
        },
        {
          "idx": "3",
          "name": "Michael Rosen",
          "img": "https://i.pinimg.com/736x/c3/67/ce/c367ce675b571ef852f1835cb3fed499.jpg",
          "comment": "Nice",
          "rating": "5"
        }
      ]
    },
    {
      "_id": "8",
      "title": "Book 8",
      "description": "Là một trong những quyển sách Việt Nam bán chạy nhất năm 2010, Tôi thấy hoa vàng trên cỏ xanh đã được tái bản ngay trong ngày phát hành đầu tiên, với tổng số bản in lên đến hơn 20.000 bản.",
      "content": "Một câu chuyện dài lắm",
      "price": 17,
      "count": 18,
      "image": "https://images.unsplash.com/photo-1668434177416-525261283120?ixlib=rb-4.0.3&ixid=MnwxMjA3fDB8MHxwaG90by1wYWdlfHx8fGVufDB8fHx8&auto=format&fit=crop&w=1035&q=80",
      "author": "Nguyễn Nhật Ánh",
      "genre": "novel",
      "publisher": "NXB Tuổi Trẻ",
      "pages": "300",
      "language": "Tiếng Việt",
      "feedbacks": [
        {
          "idx": "1",
          "name": "Joji",
          "img": "https://i.pinimg.com/736x/fa/7f/4b/fa7f4b715e0bd97be8513d0179ef795d.jpg",
          "comment": "Poor",
          "rating": "1"
        },
        {
          "idx": "2",
          "name": "Cristiano",
          "img": "https://i.pinimg.com/736x/38/29/fb/3829fb37e22dc3ae8fb0e834b33602cc.jpg",
          "comment": "Siiiiiiiiiiii",
          "rating": "3"
        },
        {
          "idx": "3",
          "name": "Michael Rosen",
          "img": "https://i.pinimg.com/736x/c3/67/ce/c367ce675b571ef852f1835cb3fed499.jpg",
          "comment": "Nice",
          "rating": "5"
        }
      ]
    },
    {
      "_id": "9",
      "title": "Book 9",
      "description": "Là một trong những quyển sách Việt Nam bán chạy nhất năm 2010, Tôi thấy hoa vàng trên cỏ xanh đã được tái bản ngay trong ngày phát hành đầu tiên, với tổng số bản in lên đến hơn 20.000 bản.",
      "content": "Một câu chuyện dài lắm",
      "price": 17,
      "count": 15,
      "image": "https://images.unsplash.com/photo-1668112055980-bca362d15815?ixlib=rb-4.0.3&ixid=MnwxMjA3fDB8MHxwaG90by1wYWdlfHx8fGVufDB8fHx8&auto=format&fit=crop&w=3830&q=80",
      "author": "Nguyễn Nhật Ánh",
      "genre": "novel",
      "publisher": "NXB Tuổi Trẻ",
      "pages": "300",
      "language": "Tiếng Việt",
      "feedbacks": [
        {
          "idx": "1",
          "name": "Joji",
          "img": "https://i.pinimg.com/736x/fa/7f/4b/fa7f4b715e0bd97be8513d0179ef795d.jpg",
          "comment": "Poor",
          "rating": "1"
        },
        {
          "idx": "2",
          "name": "Cristiano",
          "img": "https://i.pinimg.com/736x/38/29/fb/3829fb37e22dc3ae8fb0e834b33602cc.jpg",
          "comment": "Siiiiiiiiiiii",
          "rating": "3"
        },
        {
          "idx": "3",
          "name": "Michael Rosen",
          "img": "https://i.pinimg.com/736x/c3/67/ce/c367ce675b571ef852f1835cb3fed499.jpg",
          "comment": "Nice",
          "rating": "5"
        }
      ]
    },
    {
      "_id": "10",
      "title": "Book 10",
      "description": "Là một trong những quyển sách Việt Nam bán chạy nhất năm 2010, Tôi thấy hoa vàng trên cỏ xanh đã được tái bản ngay trong ngày phát hành đầu tiên, với tổng số bản in lên đến hơn 20.000 bản.",
      "content": "Một câu chuyện dài lắm",
      "price": 17,
      "count": 15,
      "image": "https://images.unsplash.com/photo-1668112055980-bca362d15815?ixlib=rb-4.0.3&ixid=MnwxMjA3fDB8MHxwaG90by1wYWdlfHx8fGVufDB8fHx8&auto=format&fit=crop&w=3830&q=80",
      "author": "Nguyễn Nhật Ánh",
      "genre": "novel",
      "publisher": "NXB Tuổi Trẻ",
      "pages": "300",
      "language": "Tiếng Việt",
      "feedbacks": [
        {
          "idx": "1",
          "name": "Joji",
          "img": "https://i.pinimg.com/736x/fa/7f/4b/fa7f4b715e0bd97be8513d0179ef795d.jpg",
          "comment": "Poor",
          "rating": "1"
        },
        {
          "idx": "2",
          "name": "Cristiano",
          "img": "https://i.pinimg.com/736x/38/29/fb/3829fb37e22dc3ae8fb0e834b33602cc.jpg",
          "comment": "Siiiiiiiiiiii",
          "rating": "3"
        },
        {
          "idx": "3",
          "name": "Michael Rosen",
          "img": "https://i.pinimg.com/736x/c3/67/ce/c367ce675b571ef852f1835cb3fed499.jpg",
          "comment": "Nice",
          "rating": "5"
        }
      ]
    },
    {
      "_id": "11",
      "title": "Book 11",
      "description": "Là một trong những quyển sách Việt Nam bán chạy nhất năm 2010, Tôi thấy hoa vàng trên cỏ xanh đã được tái bản ngay trong ngày phát hành đầu tiên, với tổng số bản in lên đến hơn 20.000 bản.",
      "content": "Một câu chuyện dài lắm",
      "price": 17,
      "count": 15,
      "image": "https://images.unsplash.com/photo-1668112055980-bca362d15815?ixlib=rb-4.0.3&ixid=MnwxMjA3fDB8MHxwaG90by1wYWdlfHx8fGVufDB8fHx8&auto=format&fit=crop&w=3830&q=80",
      "author": "Nguyễn Nhật Ánh",
      "genre": "novel",
      "publisher": "NXB Tuổi Trẻ",
      "pages": "300",
      "language": "Tiếng Việt",
      "feedbacks": [
        {
          "idx": "1",
          "name": "Joji",
          "img": "https://i.pinimg.com/736x/fa/7f/4b/fa7f4b715e0bd97be8513d0179ef795d.jpg",
          "comment": "Poor",
          "rating": "1"
        },
        {
          "idx": "2",
          "name": "Cristiano",
          "img": "https://i.pinimg.com/736x/38/29/fb/3829fb37e22dc3ae8fb0e834b33602cc.jpg",
          "comment": "Siiiiiiiiiiii",
          "rating": "3"
        },
        {
          "idx": "3",
          "name": "Michael Rosen",
          "img": "https://i.pinimg.com/736x/c3/67/ce/c367ce675b571ef852f1835cb3fed499.jpg",
          "comment": "Nice",
          "rating": "5"
        }
      ]
    },
    {
      "_id": "12",
      "title": "Book 12",
      "description": "Là một trong những quyển sách Việt Nam bán chạy nhất năm 2010, Tôi thấy hoa vàng trên cỏ xanh đã được tái bản ngay trong ngày phát hành đầu tiên, với tổng số bản in lên đến hơn 20.000 bản.",
      "content": "Một câu chuyện dài lắm",
      "price": 17,
      "count": 11,
      "image": "https://images.unsplash.com/photo-1668112055980-bca362d15815?ixlib=rb-4.0.3&ixid=MnwxMjA3fDB8MHxwaG90by1wYWdlfHx8fGVufDB8fHx8&auto=format&fit=crop&w=3830&q=80",
      "author": "Nguyễn Nhật Ánh",
      "genre": "novel",
      "publisher": "NXB Tuổi Trẻ",
      "pages": "300",
      "language": "Tiếng Việt",
      "feedbacks": [
        {
          "idx": "1",
          "name": "Joji",
          "img": "https://i.pinimg.com/736x/fa/7f/4b/fa7f4b715e0bd97be8513d0179ef795d.jpg",
          "comment": "Poor",
          "rating": "1"
        },
        {
          "idx": "2",
          "name": "Cristiano",
          "img": "https://i.pinimg.com/736x/38/29/fb/3829fb37e22dc3ae8fb0e834b33602cc.jpg",
          "comment": "Siiiiiiiiiiii",
          "rating": "3"
        },
        {
          "idx": "3",
          "name": "Michael Rosen",
          "img": "https://i.pinimg.com/736x/c3/67/ce/c367ce675b571ef852f1835cb3fed499.jpg",
          "comment": "Nice",
          "rating": "5"
        }
      ]
    },
    {
      "_id": "13",
      "title": "Book 13",
      "description": "Là một trong những quyển sách Việt Nam bán chạy nhất năm 2010, Tôi thấy hoa vàng trên cỏ xanh đã được tái bản ngay trong ngày phát hành đầu tiên, với tổng số bản in lên đến hơn 20.000 bản.",
      "content": "Một câu chuyện dài lắm",
      "price": 17,
      "count": 15,
      "image": "https://images.unsplash.com/photo-1668112055980-bca362d15815?ixlib=rb-4.0.3&ixid=MnwxMjA3fDB8MHxwaG90by1wYWdlfHx8fGVufDB8fHx8&auto=format&fit=crop&w=3830&q=80",
      "author": "Nguyễn Nhật Ánh",
      "genre": "novel",
      "publisher": "NXB Tuổi Trẻ",
      "pages": "300",
      "language": "Tiếng Việt",
      "feedbacks": [
        {
          "idx": "1",
          "name": "Joji",
          "img": "https://i.pinimg.com/736x/fa/7f/4b/fa7f4b715e0bd97be8513d0179ef795d.jpg",
          "comment": "Poor",
          "rating": "1"
        },
        {
          "idx": "2",
          "name": "Cristiano",
          "img": "https://i.pinimg.com/736x/38/29/fb/3829fb37e22dc3ae8fb0e834b33602cc.jpg",
          "comment": "Siiiiiiiiiiii",
          "rating": "3"
        },
        {
          "idx": "3",
          "name": "Michael Rosen",
          "img": "https://i.pinimg.com/736x/c3/67/ce/c367ce675b571ef852f1835cb3fed499.jpg",
          "comment": "Nice",
          "rating": "5"
        }
      ]
    },
    {
      "_id": "14",
      "title": "Book 14",
      "description": "Là một trong những quyển sách Việt Nam bán chạy nhất năm 2010, Tôi thấy hoa vàng trên cỏ xanh đã được tái bản ngay trong ngày phát hành đầu tiên, với tổng số bản in lên đến hơn 20.000 bản.",
      "content": "Một câu chuyện dài lắm",
      "price": 17,
      "count": 15,
      "image": "https://images.unsplash.com/photo-1668112055980-bca362d15815?ixlib=rb-4.0.3&ixid=MnwxMjA3fDB8MHxwaG90by1wYWdlfHx8fGVufDB8fHx8&auto=format&fit=crop&w=3830&q=80",
      "author": "Nguyễn Nhật Ánh",
      "genre": "novel",
      "publisher": "NXB Tuổi Trẻ",
      "pages": "300",
      "language": "Tiếng Việt",
      "feedbacks": [
        {
          "idx": "1",
          "name": "Joji",
          "img": "https://i.pinimg.com/736x/fa/7f/4b/fa7f4b715e0bd97be8513d0179ef795d.jpg",
          "comment": "Poor",
          "rating": "1"
        },
        {
          "idx": "2",
          "name": "Cristiano",
          "img": "https://i.pinimg.com/736x/38/29/fb/3829fb37e22dc3ae8fb0e834b33602cc.jpg",
          "comment": "Siiiiiiiiiiii",
          "rating": "3"
        },
        {
          "idx": "3",
          "name": "Michael Rosen",
          "img": "https://i.pinimg.com/736x/c3/67/ce/c367ce675b571ef852f1835cb3fed499.jpg",
          "comment": "Nice",
          "rating": "5"
        }
      ]
    },
    {
      "_id": "15",
      "title": "Book 15",
      "description": "Là một trong những quyển sách Việt Nam bán chạy nhất năm 2010, Tôi thấy hoa vàng trên cỏ xanh đã được tái bản ngay trong ngày phát hành đầu tiên, với tổng số bản in lên đến hơn 20.000 bản.",
      "content": "Một câu chuyện dài lắm",
      "price": 17,
      "count": 15,
      "image": "https://images.unsplash.com/photo-1668112055980-bca362d15815?ixlib=rb-4.0.3&ixid=MnwxMjA3fDB8MHxwaG90by1wYWdlfHx8fGVufDB8fHx8&auto=format&fit=crop&w=3830&q=80",
      "author": "Nguyễn Nhật Ánh",
      "genre": "novel",
      "publisher": "NXB Tuổi Trẻ",
      "pages": "300",
      "language": "Tiếng Việt",
      "feedbacks": [
        {
          "idx": "1",
          "name": "Joji",
          "img": "https://i.pinimg.com/736x/fa/7f/4b/fa7f4b715e0bd97be8513d0179ef795d.jpg",
          "comment": "Poor",
          "rating": "1"
        },
        {
          "idx": "2",
          "name": "Cristiano",
          "img": "https://i.pinimg.com/736x/38/29/fb/3829fb37e22dc3ae8fb0e834b33602cc.jpg",
          "comment": "Siiiiiiiiiiii",
          "rating": "3"
        },
        {
          "idx": "3",
          "name": "Michael Rosen",
          "img": "https://i.pinimg.com/736x/c3/67/ce/c367ce675b571ef852f1835cb3fed499.jpg",
          "comment": "Nice",
          "rating": "5"
        }
      ]
    },
    {
      "_id": "16",
      "title": "Book 16",
      "description": "Là một trong những quyển sách Việt Nam bán chạy nhất năm 2010, Tôi thấy hoa vàng trên cỏ xanh đã được tái bản ngay trong ngày phát hành đầu tiên, với tổng số bản in lên đến hơn 20.000 bản.",
      "content": "Một câu chuyện dài lắm",
      "price": 17,
      "count": 122,
      "image": "https://images.unsplash.com/photo-1668112055980-bca362d15815?ixlib=rb-4.0.3&ixid=MnwxMjA3fDB8MHxwaG90by1wYWdlfHx8fGVufDB8fHx8&auto=format&fit=crop&w=3830&q=80",
      "author": "Nguyễn Nhật Ánh",
      "genre": "novel",
      "publisher": "NXB Tuổi Trẻ",
      "pages": "300",
      "language": "Tiếng Việt",
      "feedbacks": [
        {
          "idx": "1",
          "name": "Joji",
          "img": "https://i.pinimg.com/736x/fa/7f/4b/fa7f4b715e0bd97be8513d0179ef795d.jpg",
          "comment": "Poor",
          "rating": "1"
        },
        {
          "idx": "2",
          "name": "Cristiano",
          "img": "https://i.pinimg.com/736x/38/29/fb/3829fb37e22dc3ae8fb0e834b33602cc.jpg",
          "comment": "Siiiiiiiiiiii",
          "rating": "3"
        },
        {
          "idx": "3",
          "name": "Michael Rosen",
          "img": "https://i.pinimg.com/736x/c3/67/ce/c367ce675b571ef852f1835cb3fed499.jpg",
          "comment": "Nice",
          "rating": "5"
        }
      ]
    },
    {
      "_id": "18",
      "title": "Book 18",
      "description": "Là một trong những quyển sách Việt Nam bán chạy nhất năm 2010, Tôi thấy hoa vàng trên cỏ xanh đã được tái bản ngay trong ngày phát hành đầu tiên, với tổng số bản in lên đến hơn 20.000 bản.",
      "content": "Một câu chuyện dài lắm",
      "price": 17,
      "count": 122,
      "image": "https://images.unsplash.com/photo-1668112055980-bca362d15815?ixlib=rb-4.0.3&ixid=MnwxMjA3fDB8MHxwaG90by1wYWdlfHx8fGVufDB8fHx8&auto=format&fit=crop&w=3830&q=80",
      "author": "Taylor",
      "genre": "comic",
      "publisher": "NXB Tuổi Trẻ",
      "pages": "300",
      "language": "Tiếng Việt",
      "feedbacks": [
        {
          "idx": "1",
          "name": "Joji",
          "img": "https://i.pinimg.com/736x/fa/7f/4b/fa7f4b715e0bd97be8513d0179ef795d.jpg",
          "comment": "Poor",
          "rating": "1"
        },
        {
          "idx": "2",
          "name": "Cristiano",
          "img": "https://i.pinimg.com/736x/38/29/fb/3829fb37e22dc3ae8fb0e834b33602cc.jpg",
          "comment": "Siiiiiiiiiiii",
          "rating": "3"
        },
        {
          "idx": "3",
          "name": "Michael Rosen",
          "img": "https://i.pinimg.com/736x/c3/67/ce/c367ce675b571ef852f1835cb3fed499.jpg",
          "comment": "Nice",
          "rating": "5"
        }
      ]
    },
    {
      "_id": "19",
      "title": "Book 19",
      "description": "Là một trong những quyển sách Việt Nam bán chạy nhất năm 2010, Tôi thấy hoa vàng trên cỏ xanh đã được tái bản ngay trong ngày phát hành đầu tiên, với tổng số bản in lên đến hơn 20.000 bản.",
      "content": "Một câu chuyện dài lắm",
      "price": 17,
      "count": 122,
      "image": "https://images.unsplash.com/photo-1668112055980-bca362d15815?ixlib=rb-4.0.3&ixid=MnwxMjA3fDB8MHxwaG90by1wYWdlfHx8fGVufDB8fHx8&auto=format&fit=crop&w=3830&q=80",
      "author": "Taylor",
      "genre": "comic",
      "publisher": "NXB Tuổi Trẻ",
      "pages": "300",
      "language": "Tiếng Việt",
      "feedbacks": [
        {
          "idx": "1",
          "name": "Joji",
          "img": "https://i.pinimg.com/736x/fa/7f/4b/fa7f4b715e0bd97be8513d0179ef795d.jpg",
          "comment": "Poor",
          "rating": "1"
        },
        {
          "idx": "2",
          "name": "Cristiano",
          "img": "https://i.pinimg.com/736x/38/29/fb/3829fb37e22dc3ae8fb0e834b33602cc.jpg",
          "comment": "Siiiiiiiiiiii",
          "rating": "3"
        },
        {
          "idx": "3",
          "name": "Michael Rosen",
          "img": "https://i.pinimg.com/736x/c3/67/ce/c367ce675b571ef852f1835cb3fed499.jpg",
          "comment": "Nice",
          "rating": "5"
        }
      ]
    },
    {
      "_id": "20",
      "title": "Book 20",
      "description": "Là một trong những quyển sách Việt Nam bán chạy nhất năm 2010, Tôi thấy hoa vàng trên cỏ xanh đã được tái bản ngay trong ngày phát hành đầu tiên, với tổng số bản in lên đến hơn 20.000 bản.",
      "content": "Một câu chuyện dài lắm",
      "price": 17,
      "count": 122,
      "image": "https://images.unsplash.com/photo-1668112055980-bca362d15815?ixlib=rb-4.0.3&ixid=MnwxMjA3fDB8MHxwaG90by1wYWdlfHx8fGVufDB8fHx8&auto=format&fit=crop&w=3830&q=80",
      "author": "Taylor",
      "genre": "comic",
      "publisher": "NXB Tuổi Trẻ",
      "pages": "300",
      "language": "Tiếng Việt",
      "feedbacks": [
        {
          "idx": "1",
          "name": "Joji",
          "img": "https://i.pinimg.com/736x/fa/7f/4b/fa7f4b715e0bd97be8513d0179ef795d.jpg",
          "comment": "Poor",
          "rating": "1"
        },
        {
          "idx": "2",
          "name": "Cristiano",
          "img": "https://i.pinimg.com/736x/38/29/fb/3829fb37e22dc3ae8fb0e834b33602cc.jpg",
          "comment": "Siiiiiiiiiiii",
          "rating": "3"
        },
        {
          "idx": "3",
          "name": "Michael Rosen",
          "img": "https://i.pinimg.com/736x/c3/67/ce/c367ce675b571ef852f1835cb3fed499.jpg",
          "comment": "Nice",
          "rating": "5"
        }
      ]
    },
    {
      "_id": "20",
      "title": "Book 20",
      "description": "Là một trong những quyển sách Việt Nam bán chạy nhất năm 2010, Tôi thấy hoa vàng trên cỏ xanh đã được tái bản ngay trong ngày phát hành đầu tiên, với tổng số bản in lên đến hơn 20.000 bản.",
      "content": "Một câu chuyện dài lắm",
      "price": 17,
      "count": 122,
      "image": "https://images.unsplash.com/photo-1668112055980-bca362d15815?ixlib=rb-4.0.3&ixid=MnwxMjA3fDB8MHxwaG90by1wYWdlfHx8fGVufDB8fHx8&auto=format&fit=crop&w=3830&q=80",
      "author": "Taylor",
      "genre": "comic",
      "publisher": "NXB Tuổi Trẻ",
      "pages": "300",
      "language": "Tiếng Việt",
      "feedbacks": [
        {
          "idx": "1",
          "name": "Joji",
          "img": "https://i.pinimg.com/736x/fa/7f/4b/fa7f4b715e0bd97be8513d0179ef795d.jpg",
          "comment": "Poor",
          "rating": "1"
        },
        {
          "idx": "2",
          "name": "Cristiano",
          "img": "https://i.pinimg.com/736x/38/29/fb/3829fb37e22dc3ae8fb0e834b33602cc.jpg",
          "comment": "Siiiiiiiiiiii",
          "rating": "3"
        },
        {
          "idx": "3",
          "name": "Michael Rosen",
          "img": "https://i.pinimg.com/736x/c3/67/ce/c367ce675b571ef852f1835cb3fed499.jpg",
          "comment": "Nice",
          "rating": "5"
        }
      ]
    }
  ]
}
